{
  "orders": [
    {
      "name": "order1",
      "products": [
        {
          "name": "tonno e cipolle",
          "category": "pizza famiglia 2 gusti",
          "ingredients": ["wurstel", "patatine"],
          "quantity": 1
        },
        {
          "name": "birra limone",
          "category": "birra",
          "ingredients": [],
          "quantity": 1
        },
        {
          "name": "patatina piccola",
          "category": "patatine",
          "ingredients": [],
          "quantity": 2
        },
        {
          "name": "the verde",
          "category": "bibita",
          "ingredients": [],
          "quantity": 1
        },
        {
          "name": "esta the limone",
          "category": "bibita",
          "ingredients": [],
          "quantity": 1
        },
        {
          "name": "coca cola",
          "category": "bibita",
          "ingredients": [],
          "quantity": 1
        },
        {
          "name": "acqua",
          "category": "bibita",
          "ingredients": [],
          "quantity": 1
        },
        {
          "name": "pizza kebab",
          "category": "pizza famiglia 4 gusti",
          "ingredients": [
            "insalata",
            "maionese",
            "mais",
            "tonno",
            "cipolle",
            "prosciutto crudo",
            "rucola",
            "wurstel",
            "patatine"
          ],
          "quantity": 1
        },
        {
          "name": "panino pizza",
          "category": "panino pizza",
          "ingredients": ["mozzarella", "prosciutto cotto"],
          "quantity": 1
        },
        {
          "name": "margherita",
          "category": "pizza",
          "ingredients": ["filadelphia", "rucola", "brie"],
          "quantity": 1
        }
      ],
      "type": "TABLE",
      "actualTotal": 0,
      "extraPrice": 0
    },
    {
      "name": "order2",
      "products": [
        {
          "name": "acqua",
          "category": "bibita",
          "ingredients": [],
          "quantity": 1
        },
        {
          "name": "patatina piccola",
          "category": "patatine",
          "ingredients": [],
          "quantity": 1
        },
        {
          "name": "margherita",
          "category": "pizza",
          "ingredients": [],
          "quantity": 1
        },
        {
          "name": "the limone",
          "category": "bibita",
          "ingredients": [],
          "quantity": 2
        },
        {
          "name": "children",
          "category": "pizza",
          "ingredients": [],
          "quantity": 1
        }
      ],
      "type": "TABLE",
      "actualTotal": 0,
      "extraPrice": 0
    },
    {
      "name": "order3",
      "products": [
        {
          "name": "kebab piadina",
          "category": "kebab",
          "ingredients": ["-cipolle"],
          "quantity": 1
        },
        {
          "name": "kebab panino",
          "category": "kebab",
          "ingredients": ["pomodoro", "mais", "insalata", "ketchup", "yogurt"],
          "quantity": 1
        },
        {
          "name": "sprite",
          "category": "bibita",
          "ingredients": [],
          "quantity": 1
        },
        {
          "name": "pepsi",
          "category": "bibita",
          "ingredients": [],
          "quantity": 1
        }
      ],
      "type": "TABLE",
      "actualTotal": 0,
      "extraPrice": 0
    },
    {
      "name": "order4",
      "products": [
        {
          "name": "kebab panino",
          "category": "kebab",
          "ingredients": ["patatine"],
          "quantity": 1
        },
        {
          "name": "kebab panino",
          "category": "kebab",
          "ingredients": ["-cipolle", "-piccante", "-mais", "-verza rossa"],
          "quantity": 2
        }
      ],
      "type": "TAKE AWAY",
      "actualTotal": 0,
      "extraPrice": 0
    },
    {
      "name": "order5",
      "products": [
        {
          "name": "kebab panino",
          "category": "kebab",
          "ingredients": ["tutto"],
          "quantity": 1
        },
        {
          "name": "kebab panino",
          "category": "kebab",
          "ingredients": ["-cipolle"],
          "quantity": 1
        },
        {
          "name": "margherita",
          "category": "pizza",
          "ingredients": ["gamberi", "funghi"],
          "quantity": 1
        },
        {
          "name": "coca cola",
          "category": "bibita",
          "ingredients": [],
          "quantity": 1
        },
        {
          "name": "fanta",
          "category": "bibita",
          "ingredients": [],
          "quantity": 1
        },
        {
          "name": "acqua",
          "category": "bibita",
          "ingredients": [],
          "quantity": 1
        }
      ],
      "type": "TABLE",
      "actualTotal": 0,
      "extraPrice": 0
    },
    {
      "name": "order6",
      "products": [
        {
          "name": "kebab piadina",
          "category": "kebab",
          "ingredients": ["tutto"],
          "quantity": 1
        },
        {
          "name": "patatina piccola",
          "category": "patatine",
          "ingredients": [],
          "quantity": 1
        },
        {
          "name": "weissbier",
          "category": "birra",
          "ingredients": [],
          "quantity": 1
        }
      ],
      "type": "TABLE",
      "actualTotal": 0,
      "extraPrice": 0
    },
    {
      "name": "order7",
      "products": [
        {
          "name": "panino jolie",
          "category": "panino pizza",
          "ingredients": [],
          "quantity": 1
        },
        {
          "name": "patatina grande",
          "category": "patatine",
          "ingredients": [],
          "quantity": 2
        },
        {
          "name": "margherita",
          "category": "pizza",
          "ingredients": [],
          "quantity": 1
        },
        {
          "name": "patatina piccola",
          "category": "patatine",
          "ingredients": [],
          "quantity": 1
        },
        {
          "name": "coca cola",
          "category": "bibita",
          "ingredients": [],
          "quantity": 2
        },
        {
          "name": "fanta",
          "category": "bibita",
          "ingredients": [],
          "quantity": 1
        }
      ],
      "type": "TAKE AWAY",
      "actualTotal": 0,
      "extraPrice": 0
    },
    {
      "name": "order8",
      "products": [
        {
          "name": "chicken royal",
          "category": "kebab",
          "ingredients": [],
          "quantity": 1
        },
        {
          "name": "doppio cheese burger",
          "category": "kebab",
          "ingredients": [],
          "quantity": 1
        },
        {
          "name": "fanta",
          "category": "bibita",
          "ingredients": [],
          "quantity": 1
        },
        {
          "name": "acqua",
          "category": "bibita",
          "ingredients": [],
          "quantity": 1
        }
      ],
      "type": "TABLE",
      "actualTotal": 0,
      "extraPrice": 0
    },
    {
      "name": "order9",
      "products": [
        {
          "name": "piatto grande",
          "category": "kebab",
          "ingredients": ["-yogurt"],
          "quantity": 1
        },
        {
          "name": "piatto grande",
          "category": "kebab",
          "ingredients": ["carne"],
          "quantity": 1
        },
        {
          "name": "coca cola",
          "category": "bibita",
          "ingredients": [],
          "quantity": 1
        },
        {
          "name": "acqua",
          "category": "bibita",
          "ingredients": [],
          "quantity": 1
        }
      ],
      "type": "TABLE",
      "actualTotal": 0,
      "extraPrice": 0
    },
    {
      "name": "order10",
      "products": [
        {
          "name": "kebab piadina",
          "category": "kebab",
          "ingredients": ["-cipolle"],
          "quantity": 1
        },
        {
          "name": "kebab piadina",
          "category": "kebab",
          "ingredients": ["-cipolle", "-yogurt", "-piccante"],
          "quantity": 1
        },
        {
          "name": "coca cola",
          "category": "bibita",
          "ingredients": [],
          "quantity": 1
        }
      ],
      "type": "TABLE",
      "actualTotal": 0,
      "extraPrice": 0
    },
    {
      "name": "order11",
      "products": [
        {
          "name": "4 formaggi",
          "category": "pizza",
          "ingredients": [],
          "quantity": 1
        },
        {
          "name": "kebab panino",
          "category": "kebab",
          "ingredients": ["tutto"],
          "quantity": 1
        },
        {
          "name": "acqua",
          "category": "bibita",
          "ingredients": [],
          "quantity": 1
        },
        {
          "name": "coca cola",
          "category": "bibita",
          "ingredients": [],
          "quantity": 1
        },
        {
          "name": "pepsi",
          "category": "bibita",
          "ingredients": [],
          "quantity": 1
        }
      ],
      "type": "TABLE",
      "actualTotal": 0,
      "extraPrice": 0
    },
    {
      "name": "order12",
      "products": [
        {
          "name": "kebab piadina",
          "category": "kebab",
          "ingredients": ["insalata", "yogurt", "mais", "maionese", "piccante"],
          "quantity": 1
        }
      ],
      "type": "TAKE AWAY",
      "actualTotal": 0,
      "extraPrice": 0
    },
    {
      "name": "order13",
      "products": [
        {
          "name": "kebab piadina",
          "category": "kebab",
          "ingredients": [
            "insalata",
            "pomodoro",
            "mais",
            "cipolle",
            "ketchup",
            "maionese",
            "yogurt"
          ],
          "quantity": 1
        }
      ],
      "type": "TABLE",
      "actualTotal": 0,
      "extraPrice": 0
    },
    {
      "name": "order14",
      "products": [
        {
          "name": "pizza kebab",
          "category": "pizza",
          "ingredients": ["mais", "yogurt", "piccante"],
          "quantity": 1
        },
        {
          "name": "margherita",
          "category": "pizza",
          "ingredients": ["bufala"],
          "quantity": 1
        },
        {
          "name": "kebab piadina",
          "category": "kebab",
          "ingredients": ["yogurt", "ketchup"],
          "quantity": 1
        }
      ],
      "type": "TAKE AWAY",
      "actualTotal": 0,
      "extraPrice": 0
    },
    {
      "name": "order15",
      "products": [
        {
          "name": "capricciosa",
          "category": "pizza",
          "ingredients": [],
          "quantity": 1
        },
        {
          "name": "doppio cheese burger menu",
          "category": "kebab",
          "ingredients": [],
          "quantity": 1
        }
      ],
      "type": "TAKE AWAY",
      "actualTotal": 0,
      "extraPrice": 0
    },
    {
      "name": "order16",
      "products": [
        {
          "name": "pizza kebab",
          "category": "pizza",
          "ingredients": ["yogurt"],
          "quantity": 1
        },
        {
          "name": "acqua",
          "category": "bibita",
          "ingredients": [],
          "quantity": 1
        }
      ],
      "type": "TABLE",
      "actualTotal": 0,
      "extraPrice": 0
    },
    {
      "name": "order17",
      "products": [
        {
          "name": "kebab piadina",
          "category": "kebab",
          "ingredients": ["-cipolle"],
          "quantity": 1
        }
      ],
      "type": "TAKE AWAY",
      "actualTotal": 0,
      "extraPrice": 0
    },
    {
      "name": "order18",
      "products": [
        {
          "name": "patatina piccola",
          "category": "patatine",
          "ingredients": [],
          "quantity": 1
        },
        {
          "name": "prosciutto e funghi",
          "category": "pizza famiglia 2 gusti",
          "ingredients": ["pancetta", "salame piccante"],
          "quantity": 1
        }
      ],
      "type": "TAKE AWAY",
      "actualTotal": 0,
      "extraPrice": 0
    },
    {
      "name": "order19",
      "products": [
        {
          "name": "prosciutto e funghi",
          "category": "pizza",
          "ingredients": ["-pomodoro"],
          "quantity": 1
        },
        {
          "name": "speciale",
          "category": "pizza",
          "ingredients": ["-pomodoro"],
          "quantity": 1
        }
      ],
      "type": "TAKE AWAY",
      "actualTotal": 0,
      "extraPrice": 0
    },
    {
      "name": "order20",
      "products": [
        {
          "name": "gustosa",
          "category": "pizza famiglia 2 gusti",
          "ingredients": [
            "prosciutto cotto",
            "wurstel",
            "salame piccante",
            "funghi",
            "carciofi"
          ],
          "quantity": 1
        }
      ],
      "type": "TAKE AWAY",
      "actualTotal": 0,
      "extraPrice": 0
    },
    {
      "name": "order21",
      "products": [
        {
          "name": "kebab piadina menu",
          "category": "kebab",
          "ingredients": [
            "insalata",
            "verza rossa",
            "cappuccio",
            "pomodoro",
            "yogurt"
          ],
          "quantity": 1
        },
        {
          "name": "chicken royal menu",
          "category": "kebab",
          "ingredients": [],
          "quantity": 1
        }
      ],
      "type": "TABLE",
      "actualTotal": 0,
      "extraPrice": 0
    },
    {
      "name": "order22",
      "products": [
        {
          "name": "kebab panino",
          "category": "kebab",
          "ingredients": ["tutto"],
          "quantity": 1
        },
        {
          "name": "kebab piadina",
          "category": "kebab",
          "ingredients": ["tutto"],
          "quantity": 1
        },
        {
          "name": "patatina piccola",
          "category": "patatine",
          "ingredients": [],
          "quantity": 1
        }
      ],
      "type": "TAKE AWAY",
      "actualTotal": 0,
      "extraPrice": 0
    },
    {
      "name": "order23",
      "products": [
        {
          "name": "kebab panino",
          "category": "kebab",
          "ingredients": ["tutto"],
          "quantity": 1
        },
        {
          "name": "kebab piadina",
          "category": "kebab",
          "ingredients": ["tutto"],
          "quantity": 1
        },
        {
          "name": "coca cola",
          "category": "bibita",
          "ingredients": [],
          "quantity": 2
        }
      ],
      "type": "TABLE",
      "actualTotal": 0,
      "extraPrice": 0
    },
    {
      "name": "order24",
      "products": [
        {
          "name": "kebab panino menu",
          "category": "kebab",
          "ingredients": ["-verza rossa", "-cipolle"],
          "quantity": 1
        }
      ],
      "type": "TABLE",
      "actualTotal": 0,
      "extraPrice": 0
    },
    {
      "name": "order25",
      "products": [
        {
          "name": "kebab panino",
          "category": "kebab",
          "ingredients": ["verza rossa", "cappuccio", "pomodoro", "yogurt"],
          "quantity": 5
        }
      ],
      "type": "TAKE AWAY",
      "actualTotal": 0,
      "extraPrice": 0
    },
    {
      "name": "order26",
      "products": [
        {
          "name": "kebab panino",
          "category": "kebab",
          "ingredients": ["insalata", "cipolle", "mais", "maionese"],
          "quantity": 2
        },
        {
          "name": "kebab panino",
          "category": "kebab",
          "ingredients": ["carne"],
          "quantity": 2
        }
      ],
      "type": "TAKE AWAY",
      "actualTotal": 0,
      "extraPrice": 0
    },
    {
      "name": "order27",
      "products": [
        {
          "name": "kebab piadina",
          "category": "kebab",
          "ingredients": ["-pomodoro", "-piccante"],
          "quantity": 1
        }
      ],
      "type": "TAKE AWAY",
      "actualTotal": 0,
      "extraPrice": 0
    },
    {
      "name": "order28",
      "products": [
        {
          "name": "kebab piadina",
          "category": "kebab",
          "ingredients": ["insalata", "piccante"],
          "quantity": 2
        }
      ],
      "type": "TAKE AWAY",
      "actualTotal": 0,
      "extraPrice": 0
    },
    {
      "name": "order29",
      "products": [
        {
          "name": "piatto grande",
          "category": "kebab",
          "ingredients": ["-mais"],
          "quantity": 1
        },
        {
          "name": "coca zero",
          "category": "bibita",
          "ingredients": [],
          "quantity": 1
        }
      ],
      "type": "TABLE",
      "actualTotal": 0,
      "extraPrice": 0
    },
    {
      "name": "order30",
      "products": [
        {
          "name": "panino cotoletta",
          "category": "kebab",
          "ingredients": ["tutto"],
          "quantity": 1
        },
        {
          "name": "acqua",
          "category": "bibita",
          "ingredients": [],
          "quantity": 1
        }
      ],
      "type": "TABLE",
      "actualTotal": 0,
      "extraPrice": 0
    },
    {
      "name": "order31",
      "products": [
        {
          "name": "kebab piadina",
          "category": "kebab",
          "ingredients": ["insalata", "piccante", "yogurt", "patatine", "mais"],
          "quantity": 1
        },
        {
          "name": "kebab piadina",
          "category": "kebab",
          "ingredients": [
            "insalata",
            "pomodoro",
            "mais",
            "yogurt",
            "ketchup",
            "maionese",
            "patatine"
          ],
          "quantity": 1
        },
        {
          "name": "kebab piadina",
          "category": "kebab",
          "ingredients": ["insalata", "cipolle", "ketchup", "maionese"],
          "quantity": 1
        },
        {
          "name": "pizza kebab",
          "category": "pizza",
          "ingredients": [
            "insalata",
            "ketchup",
            "maionese",
            "yogurt",
            "patatine"
          ],
          "quantity": 1
        }
      ],
      "type": "TAKE AWAY",
      "actualTotal": 0,
      "extraPrice": 0
    },
    {
      "name": "order32",
      "products": [
        {
          "name": "pizza kebab",
          "category": "pizza",
          "ingredients": ["tutto"],
          "quantity": 2
        },
        {
          "name": "margherita",
          "category": "pizza",
          "ingredients": ["salsiccia"],
          "quantity": 1
        },
        {
          "name": "pizza kebab",
          "category": "pizza",
          "ingredients": ["patatine", "funghi"],
          "quantity": 1
        },
        {
          "name": "children",
          "category": "pizza",
          "ingredients": [],
          "quantity": 1
        },
        {
          "name": "capricciosa",
          "category": "pizza",
          "ingredients": [],
          "quantity": 1
        },
        {
          "name": "insalata kebab",
          "category": "kebab",
          "ingredients": ["tutto"],
          "quantity": 1
        },
        {
          "name": "heineken grande",
          "category": "birra",
          "ingredients": [],
          "quantity": 1
        },
        {
          "name": "moretti",
          "category": "birra",
          "ingredients": [],
          "quantity": 1
        }
      ],
      "type": "DELIVERY",
      "actualTotal": 51.5,
      "extraPrice": 0
    },
    {
      "name": "order33",
      "products": [
        {
          "name": "wurstel",
          "category": "pizza",
          "ingredients": [],
          "quantity": 2
        }
      ],
      "type": "TAKE AWAY",
      "actualTotal": 0,
      "extraPrice": 0
    },
    {
      "name": "order34",
      "products": [
        {
          "name": "doppio cheese burger menu",
          "category": "kebab",
          "ingredients": [],
          "quantity": 1
        },
        {
          "name": "suprema",
          "category": "pizza",
          "ingredients": ["carciofi", "grana"],
          "quantity": 1
        },
        {
          "name": "alette menu",
          "category": "kebab",
          "ingredients": [],
          "quantity": 1
        },
        {
          "name": "piatto grande",
          "category": "kebab",
          "ingredients": ["patatine"],
          "quantity": 1
        },
        {
          "name": "coca cola",
          "category": "bibita",
          "ingredients": [],
          "quantity": 1
        }
      ],
      "type": "TABLE",
      "actualTotal": 0,
      "extraPrice": 0
    },
    {
      "name": "order35",
      "products": [
        {
          "name": "piatto grande",
          "category": "kebab",
          "ingredients": ["patatine", "maionese"],
          "quantity": 4
        },
        {
          "name": "coca cola",
          "category": "bibita",
          "ingredients": [],
          "quantity": 4
        },
        {
          "name": "caffe",
          "category": "bibita",
          "ingredients": [],
          "quantity": 3
        }
      ],
      "type": "TABLE",
      "actualTotal": 0,
      "extraPrice": 0
    },
    {
      "name": "order36",
      "products": [
        {
          "name": "kebab panino",
          "category": "kebab",
          "ingredients": ["-cipolle"],
          "quantity": 1
        },
        {
          "name": "kebab panino",
          "category": "kebab",
          "ingredients": ["tutto"],
          "quantity": 1
        },
        {
          "name": "patatina grande",
          "category": "patatine",
          "ingredients": [],
          "quantity": 1
        },
        {
          "name": "peroni",
          "category": "birra",
          "ingredients": [],
          "quantity": 1
        },
        {
          "name": "fanta",
          "category": "bibita",
          "ingredients": [],
          "quantity": 1
        }
      ],
      "type": "TABLE",
      "actualTotal": 0,
      "extraPrice": 0
    },
    {
      "name": "order37",
      "products": [
        {
          "name": "kebab piadina",
          "category": "kebab",
          "ingredients": ["-mais"],
          "quantity": 1
        },
        {
          "name": "coca cola",
          "category": "bibita",
          "ingredients": [],
          "quantity": 1
        }
      ],
      "type": "TABLE",
      "actualTotal": 0,
      "extraPrice": 0
    },
    {
      "name": "order38",
      "products": [
        {
          "name": "kebab panino",
          "category": "kebab",
          "ingredients": ["-mais", "-piccante"],
          "quantity": 1
        }
      ],
      "type": "TAKE AWAY",
      "actualTotal": 0,
      "extraPrice": 0
    },
    {
      "name": "order39",
      "products": [
        {
          "name": "kebab panino",
          "category": "kebab",
          "ingredients": [
            "pomodoro",
            "insalata",
            "cipolle",
            "yogurt",
            "piccante"
          ],
          "quantity": 2
        }
      ],
      "type": "TAKE AWAY",
      "actualTotal": 0,
      "extraPrice": 0
    },
    {
      "name": "order40",
      "products": [
        {
          "name": "kebab panino",
          "category": "kebab",
          "ingredients": ["-piccante"],
          "quantity": 1
        },
        {
          "name": "kebab piadina",
          "category": "kebab",
          "ingredients": ["tutto"],
          "quantity": 1
        }
      ],
      "type": "TAKE AWAY",
      "actualTotal": 0,
      "extraPrice": 0
    },
    {
      "name": "order41",
      "products": [
        {
          "name": "pugliese",
          "category": "pizza",
          "ingredients": [],
          "quantity": 1
        },
        {
          "name": "coca cola",
          "category": "bibita",
          "ingredients": [],
          "quantity": 1
        }
      ],
      "type": "TAKE AWAY",
      "actualTotal": 0,
      "extraPrice": 0
    },
    {
      "name": "order42",
      "products": [
        {
          "name": "kebab piadina",
          "category": "kebab",
          "ingredients": ["insalata", "yogurt"],
          "quantity": 1
        },
        {
          "name": "kebab panino",
          "category": "kebab",
          "ingredients": ["insalata", "maionese"],
          "quantity": 1
        },
        {
          "name": "kebab panino",
          "category": "kebab",
          "ingredients": ["piccante", "yogurt"],
          "quantity": 1
        },
        {
          "name": "kebab panino",
          "category": "kebab",
          "ingredients": ["insalata"],
          "quantity": 1
        },
        {
          "name": "kebab panino",
          "category": "kebab",
          "ingredients": ["carne"],
          "quantity": 1
        },
        {
          "name": "panino cotoletta",
          "category": "kebab",
          "ingredients": ["maionese"],
          "quantity": 1
        }
      ],
      "type": "TAKE AWAY",
      "actualTotal": 0,
      "extraPrice": 0
    },
    {
      "name": "order43",
      "products": [
        {
          "name": "estate",
          "category": "pizza",
          "ingredients": [],
          "quantity": 1
        }
      ],
      "type": "TAKE AWAY",
      "actualTotal": 0,
      "extraPrice": 0
    },
    {
      "name": "order44",
      "products": [
        {
          "name": "kebab piadina",
          "category": "kebab",
          "ingredients": ["tutto"],
          "quantity": 1
        },
        {
          "name": "kebab piadina",
          "category": "kebab",
          "ingredients": [
            "insalata",
            "pomodoro",
            "mais",
            "yogurt",
            "patatine",
            "ketchup",
            "maionese"
          ],
          "quantity": 1
        },
        {
          "name": "kebab piadina",
          "category": "kebab",
          "ingredients": ["yogurt", "mais", "patatine", "insalata"],
          "quantity": 1
        }
      ],
      "type": "TAKE AWAY",
      "actualTotal": 0,
      "extraPrice": 0
    },
    {
      "name": "order45",
      "products": [
        {
          "name": "margherita",
          "category": "pizza",
          "ingredients": ["funghi"],
          "quantity": 1
        }
      ],
      "type": "TAKE AWAY",
      "actualTotal": 0,
      "extraPrice": 0
    },
    {
      "name": "order46",
      "products": [
        {
          "name": "capricciosa",
          "category": "pizza",
          "ingredients": ["salame piccante"],
          "quantity": 4
        }
      ],
      "type": "TAKE AWAY",
      "actualTotal": 0,
      "extraPrice": 0
    },
    {
      "name": "order47",
      "products": [
        {
          "name": "prosciutto e funghi",
          "category": "pizza",
          "ingredients": [],
          "quantity": 1
        },
        {
          "name": "kebab panino",
          "category": "kebab",
          "ingredients": ["-mais", "-yogurt"],
          "quantity": 1
        }
      ],
      "type": "TAKE AWAY",
      "actualTotal": 0,
      "extraPrice": 0
    },
    {
      "name": "order48",
      "products": [
        {
          "name": "panino jolie",
          "category": "panino pizza",
          "ingredients": [],
          "quantity": 2
        },
        {
          "name": "patatina piccola",
          "category": "patatine",
          "ingredients": [],
          "quantity": 2
        }
      ],
      "type": "DELIVERY",
      "actualTotal": 14,
      "extraPrice": 0
    },
    {
      "name": "order49",
      "products": [
        {
          "name": "kebab panino",
          "category": "kebab",
          "ingredients": ["cipolle", "insalata", "yogurt"],
          "quantity": 4
        },
        {
          "name": "prosciutto e funghi",
          "category": "pizza",
          "ingredients": [],
          "quantity": 1
        }
      ],
      "type": "DELIVERY",
      "actualTotal": 20,
      "extraPrice": 2
    },
    {
      "name": "order50",
      "products": [
        {
          "name": "4 formaggi",
          "category": "pizza",
          "ingredients": [],
          "quantity": 1
        },
        {
          "name": "margherita",
          "category": "pizza",
          "ingredients": ["tonno", "patatine"],
          "quantity": 1
        },
        {
          "name": "pizza kebab",
          "category": "pizza",
          "ingredients": ["pomodoro", "cipolle", "piccante"],
          "quantity": 2
        }
      ],
      "type": "TAKE AWAY",
      "actualTotal": 0,
      "extraPrice": 0
    },
    {
      "name": "order51",
      "products": [
        {
          "name": "panino classico",
          "category": "panino pizza",
          "ingredients": [],
          "quantity": 6
        },
        {
          "name": "margherita",
          "category": "pizza",
          "ingredients": ["prosciutto crudo"],
          "quantity": 1
        },
        {
          "name": "patatina piccola",
          "category": "patatine",
          "ingredients": [],
          "quantity": 1
        },
        {
          "name": "margherita",
          "category": "pizza",
          "ingredients": ["funghi"],
          "quantity": 1
        }
      ],
      "type": "TAKE AWAY",
      "actualTotal": 0,
      "extraPrice": 0
    },
    {
      "name": "order52",
      "products": [
        {
          "name": "diavola",
          "category": "pizza",
          "ingredients": [],
          "quantity": 1
        },
        {
          "name": "calzone",
          "category": "calzone",
          "ingredients": [],
          "quantity": 1
        },
        {
          "name": "margherita",
          "category": "pizza",
          "ingredients": [],
          "quantity": 1
        },
        {
          "name": "patatina piccola",
          "category": "patatine",
          "ingredients": [],
          "quantity": 1
        },
        {
          "name": "coca cola",
          "category": "bibita",
          "ingredients": [],
          "quantity": 2
        }
      ],
      "type": "TAKE AWAY",
      "actualTotal": 0,
      "extraPrice": 0
    },
    {
      "name": "order53",
      "products": [
        {
          "name": "vegetariana",
          "category": "pizza",
          "ingredients": [],
          "quantity": 1
        },
        {
          "name": "pizza fritta",
          "category": "pizza fritta",
          "ingredients": ["ricotta", "prosciutto cotto", "salame piccante"],
          "quantity": 1
        }
      ],
      "type": "DELIVERY",
      "actualTotal": 13,
      "extraPrice": 0
    },
    {
      "name": "order54",
      "products": [
        {
          "name": "pizza kebab",
          "category": "pizza",
          "ingredients": [
            "patatine",
            "insalata",
            "yogurt",
            "ketchup",
            "maionese"
          ],
          "quantity": 1
        },
        {
          "name": "kebab piadina",
          "category": "kebab",
          "ingredients": [
            "insalata",
            "pomodoro",
            "mais",
            "ketchup",
            "maionese"
          ],
          "quantity": 1
        }
      ],
      "type": "DELIVERY",
      "actualTotal": 12,
      "extraPrice": 2
    },
    {
      "name": "order55",
      "products": [
        {
          "name": "speciale",
          "category": "pizza",
          "ingredients": ["-salame piccante"],
          "quantity": 1
        },
        {
          "name": "leggera",
          "category": "pizza fritta",
          "ingredients": [],
          "quantity": 1
        }
      ],
      "type": "DELIVERY",
      "actualTotal": 15,
      "extraPrice": 0
    },
    {
      "name": "order56",
      "products": [
        {
          "name": "pizza kebab",
          "category": "pizza famiglia",
          "ingredients": ["patatine"],
          "quantity": 1
        }
      ],
      "type": "DELIVERY",
      "actualTotal": 0,
      "extraPrice": 0
    },
    {
      "name": "order57",
      "products": [
        {
          "name": "kebab piadina",
          "category": "kebab",
          "ingredients": ["tutto"],
          "quantity": 1
        }
      ],
      "type": "TAKE AWAY",
      "actualTotal": 0,
      "extraPrice": 0
    },
    {
      "name": "order58",
      "products": [
        {
          "name": "kebab panino",
          "category": "kebab",
          "ingredients": ["tutto"],
          "quantity": 1
        }
      ],
      "type": "TAKE AWAY",
      "actualTotal": 0,
      "extraPrice": 0
    },
    {
      "name": "order59",
      "products": [
        {
          "name": "kebab piadina",
          "category": "kebab",
          "ingredients": ["patatine", "ketchup", "maionese"],
          "quantity": 1
        },
        {
          "name": "coca zero",
          "category": "bibita",
          "ingredients": [],
          "quantity": 1
        },
        {
          "name": "kebab piadina",
          "category": "kebab",
          "ingredients": ["ketchup", "patatine", "maionese"],
          "quantity": 1
        }
      ],
      "type": "TAKE AWAY",
      "actualTotal": 0,
      "extraPrice": 0
    },
    {
      "name": "order60",
      "products": [
        {
          "name": "4 formaggi",
          "category": "pizza famiglia 2 gusti",
          "ingredients": ["salame piccante", "wurstel", "patatine"],
          "quantity": 1
        },
        {
          "name": "patatina spirale",
          "category": "patatine",
          "ingredients": [],
          "quantity": 1
        }
      ],
      "type": "DELIVERY",
      "actualTotal": 20,
      "extraPrice": 0
    },
    {
      "name": "order61",
      "products": [
        {
          "name": ""
        }
      ]
    }
  ]
}
