{
  "orders": [
    {
      "name": "order1",
      "products": [
        {
          "name": "pizza kebab",
          "category": "pizza",
          "ingredients": ["-yogurt"],
          "quantity": 1
        }
      ],
      "type": "TAKE AWAY",
      "actualTotal": 0,
      "extraPrice": 0
    },
    {
      "name": "order2",
      "products": [
        {
          "name": "kebab piadina",
          "category": "kebab",
          "ingredients": ["-mais"],
          "quantity": 1
        }
      ],
      "type": "TAKE AWAY",
      "actualTotal": 0,
      "extraPrice": 0
    },
    {
      "name": "order3",
      "products": [
        {
          "name": "capricciosa",
          "category": "pizza",
          "ingredients": ["salame piccante"],
          "quantity": 1
        },
        {
          "name": "coca cola",
          "category": "bibita",
          "ingredients": [],
          "quantity": 1
        }
      ],
      "type": "TABLE",
      "actualTotal": 0,
      "extraPrice": 0
    },
    {
      "name": "order4",
      "products": [
        {
          "name": "kebab piadina",
          "category": "kebab",
          "ingredients": [
            "patatine",
            "ketchup",
            "maionese",
            "yogurt",
            "mais",
            "pomodoro"
          ],
          "quantity": 1
        }
      ],
      "type": "TAKE AWAY",
      "actualTotal": 0,
      "extraPrice": 0
    },
    {
      "name": "order5",
      "products": [
        {
          "name": "4 formaggi",
          "category": "pizza",
          "ingredients": ["salame piccante"],
          "quantity": 1
        },
        {
          "name": "patatina grande",
          "category": "patatine",
          "ingredients": [],
          "quantity": 1
        },
        {
          "name": "kebab panino",
          "category": "kebab",
          "ingredients": ["-yogurt", "-piccante", "-cipolle"],
          "quantity": 1
        },
        {
          "name": "kebab piadina",
          "category": "kebab",
          "ingredients": ["-yogurt"],
          "quantity": 1
        }
      ],
      "type": "TAKE AWAY",
      "actualTotal": 0,
      "extraPrice": 0
    },
    {
      "name": "order6",
      "products": [
        {
          "name": "margherita",
          "category": "pizza",
          "ingredients": [],
          "quantity": 1
        },
        {
          "name": "acqua",
          "category": "bibita",
          "ingredients": [],
          "quantity": 1
        },
        {
          "name": "kebab panino",
          "category": "kebab",
          "ingredients": ["-piccante"],
          "quantity": 1
        },
        {
          "name": "coca cola",
          "category": "bibita",
          "ingredients": [],
          "quantity": 1
        },
        {
          "name": "patatina piccola",
          "category": "patatine",
          "ingredients": [],
          "quantity": 1
        }
      ],
      "type": "TABLE",
      "actualTotal": 0,
      "extraPrice": 0
    },
    {
      "name": "order7",
      "products": [
        {
          "name": "kebab piadina",
          "category": "kebab",
          "ingredients": ["-insalata"],
          "quantity": 1
        },
        {
          "name": "kebab piadina",
          "category": "kebab",
          "ingredients": ["tutto"],
          "quantity": 1
        },
        {
          "name": "acqua",
          "category": "bibita",
          "ingredients": [],
          "quantity": 1
        },
        {
          "name": "kebab piadina",
          "category": "kebab",
          "ingredients": ["ketchup", "yogurt"],
          "quantity": 1
        },
        {
          "name": "pepsi",
          "category": "bibita",
          "ingredients": [],
          "quantity": 1
        }
      ],
      "type": "TABLE",
      "actualTotal": 0,
      "extraPrice": 0
    },
    {
      "name": "order8",
      "products": [
        {
          "name": "kebab panino",
          "category": "kebab",
          "ingredients": ["insalata", "pomodoro", "yogurt"],
          "quantity": 2
        },
        {
          "name": "patatina grande",
          "category": "patatine",
          "ingredients": [],
          "quantity": 2
        }
      ],
      "type": "DELIVERY",
      "actualTotal": 12,
      "extraPrice": 0
    },
    {
      "name": "order9",
      "products": [
        {
          "name": "kebab piadina",
          "category": "kebab",
          "ingredients": ["-piccante", "-mais"],
          "quantity": 1
        }
      ],
      "type": "TAKE AWAY",
      "actualTotal": 0,
      "extraPrice": 0
    },
    {
      "name": "order10",
      "products": [
        {
          "name": "wurstel",
          "category": "pizza",
          "ingredients": [],
          "quantity": 1
        },
        {
          "name": "patatina grande",
          "category": "patatine",
          "ingredients": [],
          "quantity": 1
        },
        {
          "name": "calzone",
          "category": "calzone",
          "ingredients": [],
          "quantity": 1
        },
        {
          "name": "fanta",
          "category": "bibita",
          "ingredients": [],
          "quantity": 1
        },
        {
          "name": "sprite",
          "category": "bibita",
          "ingredients": [],
          "quantity": 1
        },
        {
          "name": "coca cola",
          "category": "bibita",
          "ingredients": [],
          "quantity": 1
        }
      ],
      "type": "TABLE",
      "actualTotal": 0,
      "extraPrice": 0
    },
    {
      "name": "order11",
      "products": [
        {
          "name": "kebab piadina",
          "category": "kebab",
          "ingredients": ["tutto"],
          "quantity": 1
        },
        {
          "name": "kebab panino",
          "category": "kebab",
          "ingredients": ["tutto"],
          "quantity": 2
        },
        {
          "name": "becks",
          "category": "birra",
          "ingredients": [],
          "quantity": 1
        }
      ],
      "type": "TABLE",
      "actualTotal": 0,
      "extraPrice": 0
    },
    {
      "name": "order12",
      "products": [
        {
          "name": "kebab panino",
          "category": "kebab",
          "ingredients": ["tutto"],
          "quantity": 2
        },
        {
          "name": "wurstel",
          "category": "pizza",
          "ingredients": ["peperoni", "salame piccante"],
          "quantity": 1
        }
      ],
      "type": "TAKE AWAY",
      "actualTotal": 0,
      "extraPrice": 0
    },
    {
      "name": "order13",
      "products": [
        {
          "name": "kebab panino",
          "category": "kebab",
          "ingredients": ["-yogurt", "-piccante"],
          "quantity": 1
        }
      ],
      "type": "TAKE AWAY",
      "actualTotal": 0,
      "extraPrice": 0
    },
    {
      "name": "order14",
      "products": [
        {
          "name": "kebab piadina",
          "category": "kebab",
          "ingredients": ["tutto"],
          "quantity": 2
        }
      ],
      "type": "TAKE AWAY",
      "actualTotal": 0,
      "extraPrice": 0
    },
    {
      "name": "order15",
      "products": [
        {
          "name": "diavola",
          "category": "pizza",
          "ingredients": [],
          "quantity": 1
        },
        {
          "name": "fanta",
          "category": "bibita",
          "ingredients": [],
          "quantity": 1
        }
      ],
      "type": "TABLE",
      "actualTotal": 0,
      "extraPrice": 0
    },
    {
      "name": "order16",
      "products": [
        {
          "name": "kebab piadina",
          "category": "kebab",
          "ingredients": ["cipolle", "mais", "cappuccio"],
          "quantity": 1
        }
      ],
      "type": "TABLE",
      "actualTotal": 0,
      "extraPrice": 0
    },
    {
      "name": "order17",
      "products": [
        {
          "name": "kebab panino",
          "category": "kebab",
          "ingredients": [
            "-cipolle",
            "-yogurt",
            "-piccante",
            "-verza rossa",
            "-cappuccio"
          ],
          "quantity": 2
        },
        {
          "name": "kebab piadina",
          "category": "kebab",
          "ingredients": ["-cipolle", "-yogurt", "-verza rossa", "-cappuccio"],
          "quantity": 1
        }
      ],
      "type": "TAKE AWAY",
      "actualTotal": 0,
      "extraPrice": 0
    },
    {
      "name": "order18",
      "products": [
        {
          "name": "kebab panino",
          "category": "kebab",
          "ingredients": ["-yogurt", "-mais"],
          "quantity": 1
        },
        {
          "name": "kebab panino",
          "category": "kebab",
          "ingredients": ["cipolle"],
          "quantity": 1
        },
        {
          "name": "anelli cipolla",
          "category": "kebab",
          "ingredients": [],
          "quantity": 1
        }
      ],
      "type": "TAKE AWAY",
      "actualTotal": 0,
      "extraPrice": 0
    },
    {
      "name": "order19",
      "products": [
        {
          "name": "piatto piccolo",
          "category": "kebab",
          "ingredients": [
            "verza rossa",
            "cappuccio",
            "insalata",
            "yogurt",
            "maionese"
          ],
          "quantity": 1
        },
        {
          "name": "coca cola",
          "category": "bibita",
          "ingredients": [],
          "quantity": 1
        }
      ],
      "type": "TABLE",
      "actualTotal": 0,
      "extraPrice": 0
    },
    {
      "name": "order20",
      "products": [
        {
          "name": "panino pizza",
          "category": "panino pizza",
          "ingredients": [
            "speck",
            "brie",
            "funghi",
            "pomodoro",
            "insalata",
            "maionese"
          ],
          "quantity": 1
        },
        {
          "name": "panino pizza",
          "category": "panino pizza",
          "ingredients": ["prosciutto crudo", "mozzarella", "zucchine"],
          "quantity": 1
        },
        {
          "name": "birra spina",
          "category": "birra",
          "ingredients": [],
          "quantity": 2
        }
      ],
      "type": "TABLE",
      "actualTotal": 0,
      "extraPrice": 0
    },
    {
      "name": "order21",
      "products": [
        {
          "name": "kebab panino",
          "category": "kebab",
          "ingredients": ["-mais"],
          "quantity": 1
        }
      ],
      "type": "TAKE AWAY",
      "actualTotal": 0,
      "extraPrice": 0
    },
    {
      "name": "order22",
      "products": [
        {
          "name": "kebab panino",
          "category": "kebab",
          "ingredients": ["patatine", "piccante", "yogurt"],
          "quantity": 1
        },
        {
          "name": "patatina grande",
          "category": "patatine",
          "ingredients": [],
          "quantity": 2
        }
      ],
      "type": "TAKE AWAY",
      "actualTotal": 0,
      "extraPrice": 0
    },
    {
      "name": "order23",
      "products": [
        {
          "name": "speciale",
          "category": "pizza",
          "ingredients": [],
          "quantity": 1
        },
        {
          "name": "jolie",
          "category": "pizza",
          "ingredients": [],
          "quantity": 1
        },
        {
          "name": "moretti",
          "category": "birra",
          "ingredients": [],
          "quantity": 1
        }
      ],
      "type": "TABLE",
      "actualTotal": 0,
      "extraPrice": 0
    },
    {
      "name": "order24",
      "products": [
        {
          "name": "pizza kebab",
          "category": "pizza",
          "ingredients": ["tutto"],
          "quantity": 1
        },
        {
          "name": "margherita",
          "category": "pizza",
          "ingredients": [],
          "quantity": 1
        }
      ],
      "type": "TAKE AWAY",
      "actualTotal": 0,
      "extraPrice": 0
    },
    {
      "name": "order25",
      "products": [
        {
          "name": "kebab panino",
          "category": "kebab",
          "ingredients": ["mais", "maionese", "ketchup"],
          "quantity": 1
        }
      ],
      "type": "TAKE AWAY",
      "actualTotal": 0,
      "extraPrice": 0
    },
    {
      "name": "order26",
      "products": [
        {
          "name": "kebab piadina",
          "category": "kebab",
          "ingredients": ["-piccante"],
          "quantity": 1
        }
      ],
      "type": "TAKE AWAY",
      "actualTotal": 0,
      "extraPrice": 0
    },
    {
      "name": "order27",
      "products": [
        {
          "name": "piatto grande",
          "category": "kebab",
          "ingredients": ["-piccante"],
          "quantity": 2
        },
        {
          "name": "capricciosa",
          "category": "pizza",
          "ingredients": [],
          "quantity": 1
        }
      ],
      "type": "DELIVERY",
      "actualTotal": 20.5,
      "extraPrice": 2
    },
    {
      "name": "order28",
      "products": [
        {
          "name": "kebab panino",
          "category": "kebab",
          "ingredients": ["-mais"],
          "quantity": 1
        }
      ],
      "type": "TAKE AWAY",
      "actualTotal": 0,
      "extraPrice": 0
    },
    {
      "name": "order29",
      "products": [
        {
          "name": "pizza kebab",
          "category": "pizza",
          "ingredients": ["carne"],
          "quantity": 2
        },
        {
          "name": "patatina grande",
          "category": "patatine",
          "ingredients": [],
          "quantity": 1
        }
      ],
      "type": "TAKE AWAY",
      "actualTotal": 0,
      "extraPrice": 0
    },
    {
      "name": "order30",
      "products": [
        {
          "name": "crudo e panna",
          "category": "pizza",
          "ingredients": [],
          "quantity": 1
        },
        {
          "name": "pepsi",
          "category": "bibita",
          "ingredients": [],
          "quantity": 1
        },
        {
          "name": "monster",
          "category": "bibita",
          "ingredients": [],
          "quantity": 1
        }
      ],
      "type": "TABLE",
      "actualTotal": 0,
      "extraPrice": 0
    },
    {
      "name": "order31",
      "products": [
        {
          "name": "kebab panino",
          "category": "kebab",
          "ingredients": ["-mais"],
          "quantity": 1
        }
      ],
      "type": "TAKE AWAY",
      "actualTotal": 0,
      "extraPrice": 0
    },
    {
      "name": "order32",
      "products": [
        {
          "name": "kebab panino",
          "category": "kebab",
          "ingredients": ["tutto"],
          "quantity": 2
        }
      ],
      "type": "TAKE AWAY",
      "actualTotal": 0,
      "extraPrice": 0
    },
    {
      "name": "order33",
      "products": [
        {
          "name": "margherita",
          "category": "pizza",
          "ingredients": ["tonno", "patatine"],
          "quantity": 1
        },
        {
          "name": "acqua",
          "category": "bibita",
          "ingredients": [],
          "quantity": 1
        }
      ],
      "type": "TABLE",
      "actualTotal": 0,
      "extraPrice": 0
    },
    {
      "name": "order34",
      "products": [
        {
          "name": "margherita",
          "category": "pizza",
          "ingredients": ["patatine"],
          "quantity": 2
        },
        {
          "name": "capricciosa",
          "category": "pizza",
          "ingredients": [],
          "quantity": 1
        }
      ],
      "type": "TAKE AWAY",
      "actualTotal": 0,
      "extraPrice": 0
    },
    {
      "name": "order35",
      "products": [
        {
          "name": "4 formaggi",
          "category": "pizza",
          "ingredients": [],
          "quantity": 1
        },
        {
          "name": "panino classico",
          "category": "panino pizza",
          "ingredients": [],
          "quantity": 1
        },
        {
          "name": "anelli cipolla",
          "category": "kebab",
          "ingredients": [],
          "quantity": 1
        }
      ],
      "type": "DELIVERY",
      "actualTotal": 13.5,
      "extraPrice": 0
    },
    {
      "name": "order36",
      "products": [
        {
          "name": "children",
          "category": "pizza",
          "ingredients": [],
          "quantity": 1
        },
        {
          "name": "kebab panino menu",
          "category": "kebab",
          "ingredients": ["tutto"],
          "quantity": 1
        },
        {
          "name": "kebab piadina",
          "category": "kebab",
          "ingredients": ["-piccante"],
          "quantity": 1
        },
        {
          "name": "kebab piadina menu",
          "category": "kebab",
          "ingredients": ["tutto"],
          "quantity": 1
        }
      ],
      "type": "DELIVERY",
      "actualTotal": 24.5,
      "extraPrice": 0
    },
    {
      "name": "order37",
      "products": [
        {
          "name": "kebab panino",
          "category": "kebab",
          "ingredients": ["-piccante"],
          "quantity": 4
        }
      ],
      "type": "DELIVERY",
      "actualTotal": 16,
      "extraPrice": 0
    },
    {
      "name": "order38",
      "products": [
        {
          "name": "capricciosa",
          "category": "pizza",
          "ingredients": [],
          "quantity": 1
        },
        {
          "name": "pizza kebab",
          "category": "pizza",
          "ingredients": ["tutto"],
          "quantity": 1
        },
        {
          "name": "patatina grande",
          "category": "patatine",
          "ingredients": [],
          "quantity": 1
        },
        {
          "name": "moretti",
          "category": "birra",
          "ingredients": [],
          "quantity": 2
        }
      ],
      "type": "DELIVERY",
      "actualTotal": 23,
      "extraPrice": 2
    },
    {
      "name": "order39",
      "products": [
        {
          "name": "kebab panino",
          "category": "kebab",
          "ingredients": ["-piccante"],
          "quantity": 3
        },
        {
          "name": "kebab piadina",
          "category": "kebab",
          "ingredients": ["-piccante"],
          "quantity": 2
        },
        {
          "name": "capricciosa",
          "category": "pizza famiglia",
          "ingredients": [],
          "quantity": 1
        }
      ],
      "type": "DELIVERY",
      "actualTotal": 34,
      "extraPrice": 0
    },
    {
      "name": "order40",
      "products": [
        {
          "name": "margherita",
          "category": "pizza",
          "ingredients": ["tonno", "carciofi"],
          "quantity": 1
        },
        {
          "name": "children",
          "category": "pizza",
          "ingredients": ["salsiccia"],
          "quantity": 1
        }
      ],
      "type": "TAKE AWAY",
      "actualTotal": 0,
      "extraPrice": 0
    },
    {
      "name": "order41",
      "products": [
        {
          "name": "kebab piadina",
          "category": "kebab",
          "ingredients": ["tutto"],
          "quantity": 1
        },
        {
          "name": "kebab panino",
          "category": "kebab",
          "ingredients": ["tutto"],
          "quantity": 1
        },
        {
          "name": "patatina grande",
          "category": "patatine",
          "ingredients": [],
          "quantity": 1
        }
      ],
      "type": "DELIVERY",
      "actualTotal": 12,
      "extraPrice": 0
    },
    {
      "name": "order42",
      "products": [
        {
          "name": "kebab panino",
          "category": "kebab",
          "ingredients": [
            "insalata",
            "cipolle",
            "cappuccio",
            "patatine",
            "ketchup",
            "piccante"
          ],
          "quantity": 1
        },
        {
          "name": "kebab panino",
          "category": "kebab",
          "ingredients": [
            "insalata",
            "cipolle",
            "cappuccio",
            "maionese",
            "yogurt",
            "patatine"
          ],
          "quantity": 1
        }
      ],
      "type": "TAKE AWAY",
      "actualTotal": 0,
      "extraPrice": 0
    },
    {
      "name": "order43",
      "products": [
        {
          "name": "margherita",
          "category": "pizza",
          "ingredients": [],
          "quantity": 1
        },
        {
          "name": "piatto grande",
          "category": "kebab",
          "ingredients": ["cipolle", "maionese", "ketchup", "mais"],
          "quantity": 1
        },
        {
          "name": "veneta",
          "category": "pizza",
          "ingredients": [],
          "quantity": 2
        }
      ],
      "type": "TAKE AWAY",
      "actualTotal": 0,
      "extraPrice": 0
    },
    {
      "name": "order44",
      "products": [
        {
          "name": "4 stagioni",
          "category": "pizza",
          "ingredients": [],
          "quantity": 1
        },
        {
          "name": "frutti di mare",
          "category": "pizza",
          "ingredients": [],
          "quantity": 1
        },
        {
          "name": "diavola",
          "category": "pizza",
          "ingredients": [],
          "quantity": 1
        }
      ],
      "type": "DELIVERY",
      "actualTotal": 15,
      "extraPrice": 0
    },
    {
      "name": "order45",
      "products": [
        {
          "name": "chicken royal",
          "category": "kebab",
          "ingredients": [],
          "quantity": 1
        },
        {
          "name": "diavola",
          "category": "pizza",
          "ingredients": [],
          "quantity": 1
        }
      ],
      "type": "TAKE AWAY",
      "actualTotal": 0,
      "extraPrice": 0
    },
    {
      "name": "order46",
      "products": [
        {
          "name": "prosciutto",
          "category": "pizza",
          "ingredients": ["salsiccia"],
          "quantity": 1
        },
        {
          "name": "kebab panino",
          "category": "kebab",
          "ingredients": ["-verza rossa", "-piccante"],
          "quantity": 2
        },
        {
          "name": "kebab piadina",
          "category": "kebab",
          "ingredients": ["-verza rossa", "-piccante"],
          "quantity": 1
        }
      ],
      "type": "TAKE AWAY",
      "actualTotal": 0,
      "extraPrice": 0
    },
    {
      "name": "order47",
      "products": [
        {
          "name": "kebab panino",
          "category": "kebab",
          "ingredients": ["-piccante"],
          "quantity": 1
        },
        {
          "name": "kebab piadina",
          "category": "kebab",
          "ingredients": ["-pomodoro"],
          "quantity": 1
        },
        {
          "name": "coca cola",
          "category": "bibita",
          "ingredients": [],
          "quantity": 3
        }
      ],
      "type": "TAKE AWAY",
      "actualTotal": 0,
      "extraPrice": 0
    },
    {
      "name": "order48",
      "products": [
        {
          "name": "piatto grande",
          "category": "kebab",
          "ingredients": ["patatine"],
          "quantity": 1
        },
        {
          "name": "coca cola",
          "category": "bibita",
          "ingredients": [],
          "quantity": 1
        }
      ],
      "type": "TAKE AWAY",
      "actualTotal": 0,
      "extraPrice": 0
    },
    {
      "name": "order49",
      "products": [
        {
          "name": "4 formaggi",
          "category": "pizza",
          "ingredients": [],
          "quantity": 1
        }
      ],
      "type": "TABLE",
      "actualTotal": 0,
      "extraPrice": 0
    },
    {
      "name": "order50",
      "products": [
        {
          "name": "kebab piadina",
          "category": "kebab",
          "ingredients": [
            "insalata",
            "mais",
            "yogurt",
            "piccante",
            "maionese",
            "patatine"
          ],
          "quantity": 1
        }
      ],
      "type": "TAKE AWAY",
      "actualTotal": 0,
      "extraPrice": 0
    },
    {
      "name": "order51",
      "products": [
        {
          "name": "panino falafel",
          "category": "kebab",
          "ingredients": ["insalata", "yogurt"],
          "quantity": 2
        },
        {
          "name": "heineken grande",
          "category": "birra",
          "ingredients": [],
          "quantity": 2
        }
      ],
      "type": "TAKE AWAY",
      "actualTotal": 0,
      "extraPrice": 0
    },
    {
      "name": "order52",
      "products": [
        {
          "name": "piatto grande",
          "category": "kebab",
          "ingredients": ["carne"],
          "quantity": 1
        },
        {
          "name": "margherita",
          "category": "pizza",
          "ingredients": [],
          "quantity": 1
        },
        {
          "name": "kebab piadina",
          "category": "kebab",
          "ingredients": [
            "insalata",
            "mais",
            "cipolle",
            "verza rossa",
            "cappuccio",
            "yogurt",
            "piccante"
          ],
          "quantity": 1
        }
      ],
      "type": "TAKE AWAY",
      "actualTotal": 0,
      "extraPrice": 0
    },
    {
      "name": "order53",
      "products": [
        {
          "name": "margherita",
          "category": "pizza",
          "ingredients": [],
          "quantity": 1
        },
        {
          "name": "vegetariana",
          "category": "pizza",
          "ingredients": [],
          "quantity": 1
        }
      ],
      "type": "TAKE AWAY",
      "actualTotal": 0,
      "extraPrice": 0
    },
    {
      "name": "order54",
      "products": [
        {
          "name": "kebab panino",
          "category": "kebab",
          "ingredients": ["mais", "insalata", "yogurt"],
          "quantity": 1
        }
      ],
      "type": "TAKE AWAY",
      "actualTotal": 0,
      "extraPrice": 0
    },
    {
      "name": "order55",
      "products": [
        {
          "name": "frutti di mare",
          "category": "pizza",
          "ingredients": [],
          "quantity": 1
        }
      ],
      "type": "TAKE AWAY",
      "actualTotal": 0,
      "extraPrice": 0
    },
    {
      "name": "order56",
      "products": [
        {
          "name": "margherita",
          "category": "pizza",
          "ingredients": [],
          "quantity": 1
        },
        {
          "name": "prosciutto e funghi",
          "category": "pizza",
          "ingredients": [],
          "quantity": 1
        },
        {
          "name": "vegetariana",
          "category": "pizza",
          "ingredients": ["acciughe"],
          "quantity": 1
        },
        {
          "name": "pizza kebab",
          "category": "pizza",
          "ingredients": ["tutto"],
          "quantity": 1
        },
        {
          "name": "esta the limone",
          "category": "bibita",
          "ingredients": [],
          "quantity": 1
        }
      ],
      "type": "TAKE AWAY",
      "actualTotal": 0,
      "extraPrice": 0
    },
    {
      "name": "order57",
      "products": [
        {
          "name": "kebab panino",
          "category": "kebab",
          "ingredients": ["ketchup", "maionese", "patatine", "piccante"],
          "quantity": 1
        },
        {
          "name": "kebab panino",
          "category": "kebab",
          "ingredients": [
            "mais",
            "pomodoro",
            "insalata",
            "patatine",
            "maionese",
            "ketchup",
            "yogurt"
          ],
          "quantity": 1
        }
      ],
      "type": "TAKE AWAY",
      "actualTotal": 0,
      "extraPrice": 0
    },
    {
      "name": "order58",
      "products": [
        {
          "name": "alette",
          "category": "kebab",
          "ingredients": [],
          "quantity": 2
        },
        {
          "name": "patatina piccola",
          "category": "patatine",
          "ingredients": [],
          "quantity": 1
        },
        {
          "name": "coca cola",
          "category": "bibita",
          "ingredients": [],
          "quantity": 1
        },
        {
          "name": "pizza kebab",
          "category": "pizza",
          "ingredients": ["ketchup", "maionese", "insalata", "patatine"],
          "quantity": 1
        },
        {
          "name": "peroni",
          "category": "birra",
          "ingredients": [],
          "quantity": 2
        },
        {
          "name": "diavola",
          "category": "pizza",
          "ingredients": [],
          "quantity": 1
        }
      ],
      "type": "TABLE",
      "actualTotal": 0,
      "extraPrice": 0
    },
    {
      "name": "order59",
      "products": [
        {
          "name": "patatina grande",
          "category": "patatine",
          "ingredients": [],
          "quantity": 1
        },
        {
          "name": "alette",
          "category": "kebab",
          "ingredients": [],
          "quantity": 1
        },
        {
          "name": "fanta",
          "category": "bibita",
          "ingredients": [],
          "quantity": 2
        },
        {
          "name": "red bull",
          "category": "bibita",
          "ingredients": [],
          "quantity": 1
        }
      ],
      "type": "TABLE",
      "actualTotal": 0,
      "extraPrice": 0
    },
    {
      "name": "order60",
      "products": [
        {
          "name": "margherita",
          "category": "pizza",
          "ingredients": [],
          "quantity": 1
        },
        {
          "name": "diavola",
          "category": "pizza",
          "ingredients": [],
          "quantity": 1
        },
        {
          "name": "margherita",
          "category": "pizza",
          "ingredients": ["patatine"],
          "quantity": 1
        },
        {
          "name": "margherita",
          "category": "pizza",
          "ingredients": ["patate forno"],
          "quantity": 1
        },
        {
          "name": "coca grande",
          "category": "bibita",
          "ingredients": [],
          "quantity": 1
        },
        {
          "name": "acqua",
          "category": "bibita",
          "ingredients": [],
          "quantity": 1
        }
      ],
      "type": "TAKE AWAY",
      "actualTotal": 0,
      "extraPrice": 0
    },
    {
      "name": "order61",
      "products": [
        {
          "name": "tonno e cipolle",
          "category": "pizza",
          "ingredients": [],
          "quantity": 2
        },
        {
          "name": "coca cola",
          "category": "bibita",
          "ingredients": [],
          "quantity": 2
        }
      ],
      "type": "TABLE",
      "actualTotal": 0,
      "extraPrice": 0
    },
    {
      "name": "order62",
      "products": [
        {
          "name": "piatto grande",
          "category": "kebab",
          "ingredients": ["-cipolle", "-yogurt", "-piccante"],
          "quantity": 2
        }
      ],
      "type": "TAKE AWAY",
      "actualTotal": 0,
      "extraPrice": 0
    },
    {
      "name": "order63",
      "products": [
        {
          "name": "margherita",
          "category": "pizza",
          "ingredients": [],
          "quantity": 2
        },
        {
          "name": "margherita",
          "category": "pizza",
          "ingredients": ["patatine"],
          "quantity": 1
        },
        {
          "name": "kebab piadina",
          "category": "kebab",
          "ingredients": ["carne"],
          "quantity": 1
        },
        {
          "name": "pepsi",
          "category": "bibita",
          "ingredients": [],
          "quantity": 1
        },
        {
          "name": "coca cola",
          "category": "bibita",
          "ingredients": [],
          "quantity": 1
        }
      ],
      "type": "TAKE AWAY",
      "actualTotal": 0,
      "extraPrice": 0
    },
    {
      "name": "order64",
      "products": [
        {
          "name": "pizza kebab",
          "category": "pizza famiglia 2 gusti",
          "ingredients": ["-piccante", "prosciutto cotto"],
          "quantity": 1
        }
      ],
      "type": "TAKE AWAY",
      "actualTotal": 0,
      "extraPrice": 0
    },
    {
      "name": "order65",
      "products": [
        {
          "name": "pizza kebab",
          "category": "pizza",
          "ingredients": ["yogurt", "patatine", "maionese"],
          "quantity": 1
        }
      ],
      "type": "TAKE AWAY",
      "actualTotal": 0,
      "extraPrice": 0
    },
    {
      "name": "order66",
      "products": [
        {
          "name": "margherita",
          "category": "pizza",
          "ingredients": [],
          "quantity": 4
        }
      ],
      "type": "TAKE AWAY",
      "actualTotal": 0,
      "extraPrice": 0
    },
    {
      "name": "order67",
      "products": [
        {
          "name": "margherita",
          "category": "pizza",
          "ingredients": [],
          "quantity": 1
        },
        {
          "name": "coca cola",
          "category": "bibita",
          "ingredients": [],
          "quantity": 1
        }
      ],
      "type": "TABLE",
      "actualTotal": 0,
      "extraPrice": 0
    },
    {
      "name": "order68",
      "products": [
        {
          "name": "margherita",
          "category": "pizza",
          "ingredients": [],
          "quantity": 1
        }
      ],
      "type": "TAKE AWAY",
      "actualTotal": 0,
      "extraPrice": 0
    },
    {
      "name": "order69",
      "products": [
        {
          "name": "panino jolie",
          "category": "panino pizza",
          "ingredients": [],
          "quantity": 1
        }
      ],
      "type": "TAKE AWAY",
      "actualTotal": 0,
      "extraPrice": 0
    },
    {
      "name": "order70",
      "products": [
        {
          "name": "kebab panino",
          "category": "kebab",
          "ingredients": ["patatine", "insalata", "maionese"],
          "quantity": 1
        },
        {
          "name": "kebab panino",
          "category": "kebab",
          "ingredients": ["-piccante"],
          "quantity": 1
        }
      ],
      "type": "TAKE AWAY",
      "actualTotal": 0,
      "extraPrice": 0
    },
    {
      "name": "order71",
      "products": [
        {
          "name": "kebab panino",
          "category": "kebab",
          "ingredients": ["tutto"],
          "quantity": 3
        },
        {
          "name": "kebab panino",
          "category": "kebab",
          "ingredients": ["-piccante"],
          "quantity": 3
        }
      ],
      "type": "TAKE AWAY",
      "actualTotal": 0,
      "extraPrice": 0
    },
    {
      "name": "order72",
      "products": [
        {
          "name": "panino jolie",
          "category": "panino pizza",
          "ingredients": [],
          "quantity": 1
        },
        {
          "name": "margherita",
          "category": "pizza",
          "ingredients": ["prosciutto crudo"],
          "quantity": 1
        }
      ],
      "type": "TAKE AWAY",
      "actualTotal": 0,
      "extraPrice": 0
    },
    {
      "name": "order73",
      "products": [
        {
          "name": "piatto piccolo",
          "category": "kebab",
          "ingredients": ["-cipolle", "-piccante"],
          "quantity": 1
        },
        {
          "name": "kebab panino",
          "category": "kebab",
          "ingredients": ["piccante"],
          "quantity": 1
        },
        {
          "name": "kebab panino",
          "category": "kebab",
          "ingredients": ["maionese"],
          "quantity": 1
        },
        {
          "name": "patatina grande",
          "category": "patatine",
          "ingredients": [],
          "quantity": 1
        }
      ],
      "type": "DELIVERY",
      "actualTotal": 16,
      "extraPrice": 0
    },
    {
      "name": "order74",
      "products": [
        {
          "name": "kebab piadina",
          "category": "kebab",
          "ingredients": ["patatine", "maionese"],
          "quantity": 1
        },
        {
          "name": "wurstel",
          "category": "pizza",
          "ingredients": [],
          "quantity": 1
        },
        {
          "name": "kebab piadina menu",
          "category": "kebab",
          "ingredients": ["insalata", "pomodoro", "maionese", "cipolle"],
          "quantity": 1
        },
        {
          "name": "kebab piadina menu",
          "category": "kebab",
          "ingredients": ["insalata", "pomodoro", "patatine", "piccante"],
          "quantity": 1
        },
        {
          "name": "kebab piadina menu",
          "category": "kebab",
          "ingredients": ["insalata", "maionese", "patatine"],
          "quantity": 1
        },
        {
          "name": "moretti",
          "category": "birra",
          "ingredients": [],
          "quantity": 3
        }
      ],
      "type": "DELIVERY",
      "actualTotal": 39,
      "extraPrice": 0
    },
    {
      "name": "order75",
      "products": [
        {
          "name": "marinara",
          "category": "pizza",
          "ingredients": [],
          "quantity": 1
        },
        {
          "name": "margherita",
          "category": "pizza",
          "ingredients": [],
          "quantity": 1
        },
        {
          "name": "patatina grande",
          "category": "patatine",
          "ingredients": [],
          "quantity": 1
        }
      ],
      "type": "DELIVERY",
      "actualTotal": 12,
      "extraPrice": 0
    },
    {
      "name": "order76",
      "products": [
        {
          "name": "piatto grande",
          "category": "patatine",
          "ingredients": ["mais", "insalata", "yogurt", "patatine"],
          "quantity": 1
        },
        {
          "name": "piatto grande",
          "category": "patatine",
          "ingredients": ["yogurt", "maionese"],
          "quantity": 1
        },
        {
          "name": "piatto grande",
          "category": "patatine",
          "ingredients": ["-mais"],
          "quantity": 1
        },
        {
          "name": "heineken grande",
          "category": "birra",
          "ingredients": [],
          "quantity": 3
        }
      ],
      "type": "TABLE",
      "actualTotal": 0,
      "extraPrice": 0
    },
    {
      "name": "order77",
      "products": [
        {
          "name": "veneta",
          "category": "pizza",
          "ingredients": [],
          "quantity": 1
        },
        {
          "name": "gozzo",
          "category": "pizza",
          "ingredients": [],
          "quantity": 1
        },
        {
          "name": "piatto piccolo",
          "category": "kebab",
          "ingredients": ["carne"],
          "quantity": 1
        },
        {
          "name": "wurstel",
          "category": "pizza",
          "ingredients": ["funghi"],
          "quantity": 1
        },
        {
          "name": "patatina grande",
          "category": "patatine",
          "ingredients": [],
          "quantity": 1
        }
      ],
      "type": "DELIVERY",
      "actualTotal": 28,
      "extraPrice": 0
    },
    {
      "name": "order78",
      "products": [
        {
          "name": "kebab piadina menu",
          "category": "kebab",
          "ingredients": ["insalata", "pomodoro", "yogurt", "piccante"],
          "quantity": 1
        },
        {
          "name": "coca cola",
          "category": "bibita",
          "ingredients": [],
          "quantity": 2
        },
        {
          "name": "diavola",
          "category": "pizza",
          "ingredients": [],
          "quantity": 1
        }
      ],
      "type": "TABLE",
      "actualTotal": 0,
      "extraPrice": 0
    },
    {
      "name": "order79",
      "products": [
        {
          "name": "kebab panino",
          "category": "kebab",
          "ingredients": ["-cipolle"],
          "quantity": 2
        },
        {
          "name": "kebab panino",
          "category": "kebab",
          "ingredients": ["tutto"],
          "quantity": 2
        },
        {
          "name": "4 formaggi",
          "category": "pizza",
          "ingredients": [],
          "quantity": 1
        }
      ],
      "type": "TAKE AWAY",
      "actualTotal": 0,
      "extraPrice": 0
    },
    {
      "name": "order80",
      "products": [
        {
          "name": "kebab panino",
          "category": "kebab",
          "ingredients": ["tutto"],
          "quantity": 2
        },
        {
          "name": "patatina piccola",
          "category": "patatine",
          "ingredients": [],
          "quantity": 1
        },
        {
          "name": "coca grande",
          "category": "bibita",
          "ingredients": [],
          "quantity": 1
        }
      ],
      "type": "TABLE",
      "actualTotal": 0,
      "extraPrice": 0
    },
    {
      "name": "order81",
      "products": [
        {
          "name": "margherita",
          "category": "pizza famiglia",
          "ingredients": [],
          "quantity": 1
        }
      ],
      "type": "TAKE AWAY",
      "actualTotal": 0,
      "extraPrice": 0
    },
    {
      "name": "order82",
      "products": [
        {
          "name": "cheese burger menu",
          "category": "kebab",
          "ingredients": [],
          "quantity": 2
        }
      ],
      "type": "DELIVERY",
      "actualTotal": 12,
      "extraPrice": 0
    },
    {
      "name": "order83",
      "products": [
        {
          "name": "piatto grande",
          "category": "kebab",
          "ingredients": ["tutto"],
          "quantity": 1
        },
        {
          "name": "margherita",
          "category": "pizza famiglia",
          "ingredients": [],
          "quantity": 1
        },
        {
          "name": "margherita",
          "category": "pizza",
          "ingredients": ["carciofi", "funghi"],
          "quantity": 1
        }
      ],
      "type": "DELIVERY",
      "actualTotal": 22.5,
      "extraPrice": 0
    },
    {
      "name": "order84",
      "products": [
        {
          "name": "margherita",
          "category": "pizza famiglia 2 gusti",
          "ingredients": ["prosciutto cotto", "funghi"],
          "quantity": 1
        }
      ],
      "type": "TAKE AWAY",
      "actualTotal": 0,
      "extraPrice": 0
    },
    {
      "name": "order85",
      "products": [
        {
          "name": "piatto grande",
          "category": "kebab",
          "ingredients": ["insalata", "pomodoro", "yogurt"],
          "quantity": 1
        },
        {
          "name": "heineken grande",
          "category": "birra",
          "ingredients": [],
          "quantity": 1
        }
      ],
      "type": "TABLE",
      "actualTotal": 0,
      "extraPrice": 0
    },
    {
      "name": "order86",
      "products": [
        {
          "name": "speciale",
          "category": "pizza",
          "ingredients": ["-salame piccante"],
          "quantity": 1
        },
        {
          "name": "leggera",
          "category": "pizza fritta",
          "ingredients": [],
          "quantity": 1
        }
      ],
      "type": "DELIVERY",
      "actualTotal": 15,
      "extraPrice": 0
    },
    {
      "name": "order87",
      "products": [
        {
          "name": "capricciosa",
          "category": "pizza",
          "ingredients": ["salame piccante", "olio piccante"],
          "quantity": 1
        },
        {
          "name": "acqua",
          "category": "bibita",
          "ingredients": [],
          "quantity": 1
        }
      ],
      "type": "TABLE",
      "actualTotal": 0,
      "extraPrice": 0
    },
    {
      "name": "order88",
      "products": [
        {
          "name": "panino jolie",
          "category": "panino pizza",
          "ingredients": [],
          "quantity": 2
        }
      ],
      "type": "TAKE AWAY",
      "actualTotal": 0,
      "extraPrice": 0
    },
    {
      "name": "order89",
      "products": [
        {
          "name": "speciale",
          "category": "pizza",
          "ingredients": [],
          "quantity": 2
        },
        {
          "name": "patatina piccola",
          "category": "patatine",
          "ingredients": [],
          "quantity": 1
        }
      ],
      "type": "TAKE AWAY",
      "actualTotal": 0,
      "extraPrice": 0
    },
    {
      "name": "order90",
      "products": [
        {
          "name": "frutti di mare",
          "category": "pizza",
          "ingredients": [],
          "quantity": 1
        },
        {
          "name": "prosciutto e funghi",
          "category": "pizza",
          "ingredients": [],
          "quantity": 1
        }
      ],
      "type": "TAKE AWAY",
      "actualTotal": 0,
      "extraPrice": 0
    },
    {
      "name": "order91",
      "products": [
        {
          "name": ""
        }
      ]
    }
  ]
}
